[{"name":"expect abstract class ViewModel","description":"com.hoc081098.kmp.viewmodel.ViewModel","location":"library/com.hoc081098.kmp.viewmodel/-view-model/index.html","searchKeys":["ViewModel","expect abstract class ViewModel","com.hoc081098.kmp.viewmodel.ViewModel"]},{"name":"expect abstract fun close()","description":"com.hoc081098.kmp.viewmodel.Closeable.close","location":"library/com.hoc081098.kmp.viewmodel/-closeable/close.html","searchKeys":["close","expect abstract fun close()","com.hoc081098.kmp.viewmodel.Closeable.close"]},{"name":"expect fun Lockable()","description":"com.hoc081098.kmp.viewmodel.Lockable.Lockable","location":"library/com.hoc081098.kmp.viewmodel/-lockable/-lockable.html","searchKeys":["Lockable","expect fun Lockable()","com.hoc081098.kmp.viewmodel.Lockable.Lockable"]},{"name":"expect fun ViewModel()","description":"com.hoc081098.kmp.viewmodel.ViewModel.ViewModel","location":"library/com.hoc081098.kmp.viewmodel/-view-model/-view-model.html","searchKeys":["ViewModel","expect fun ViewModel()","com.hoc081098.kmp.viewmodel.ViewModel.ViewModel"]},{"name":"expect fun ViewModel(vararg closeables: Closeable)","description":"com.hoc081098.kmp.viewmodel.ViewModel.ViewModel","location":"library/com.hoc081098.kmp.viewmodel/-view-model/-view-model.html","searchKeys":["ViewModel","expect fun ViewModel(vararg closeables: Closeable)","com.hoc081098.kmp.viewmodel.ViewModel.ViewModel"]},{"name":"expect fun addCloseable(closeable: Closeable)","description":"com.hoc081098.kmp.viewmodel.ViewModel.addCloseable","location":"library/com.hoc081098.kmp.viewmodel/-view-model/add-closeable.html","searchKeys":["addCloseable","expect fun addCloseable(closeable: Closeable)","com.hoc081098.kmp.viewmodel.ViewModel.addCloseable"]},{"name":"expect fun interface Closeable","description":"com.hoc081098.kmp.viewmodel.Closeable","location":"library/com.hoc081098.kmp.viewmodel/-closeable/index.html","searchKeys":["Closeable","expect fun interface Closeable","com.hoc081098.kmp.viewmodel.Closeable"]},{"name":"expect open class Lockable","description":"com.hoc081098.kmp.viewmodel.Lockable","location":"library/com.hoc081098.kmp.viewmodel/-lockable/index.html","searchKeys":["Lockable","expect open class Lockable","com.hoc081098.kmp.viewmodel.Lockable"]},{"name":"expect val viewModelScope: CoroutineScope","description":"com.hoc081098.kmp.viewmodel.ViewModel.viewModelScope","location":"library/com.hoc081098.kmp.viewmodel/-view-model/view-model-scope.html","searchKeys":["viewModelScope","expect val viewModelScope: CoroutineScope","com.hoc081098.kmp.viewmodel.ViewModel.viewModelScope"]},{"name":"fun clear()","description":"com.hoc081098.kmp.viewmodel.ViewModel.clear","location":"library/com.hoc081098.kmp.viewmodel/-view-model/clear.html","searchKeys":["clear","fun clear()","com.hoc081098.kmp.viewmodel.ViewModel.clear"]}]